task_graph/__init__.py
task_graph/core/__init__.py
task_graph/core/graph.py
task_graph/core/node.py
task_graph/core/result.py
task_graph/scheduler/__init__.py
task_graph/utils/__init__.py
task_graph/utils/error.py
task_graph/utils/mixin.py
task_graph/utils/preset.py
task_graph/visualize/__init__.py
task_graph-0.0.1.dist-info/METADATA
task_graph-0.0.1.dist-info/WHEEL
task_graph-0.0.1.dist-info/top_level.txt
task_graph-0.0.1.dist-info/RECORD
