Metadata-Version: 2.1
Name: task-graph
Version: 0.0.1
Summary: Make computer lazy and build a dynamic task graph for your project!
Home-page: https://github.com/loopyme/Task-Graph
Author: loopyme
Author-email: peter@mail.loopy.tech
License: MIT
Keywords: task-graph task-manager lazy
Platform: UNKNOWN
Classifier: Development Status :: 4 - Beta
Classifier: Topic :: Software Development :: Build Tools
Classifier: License :: OSI Approved :: MIT License
Classifier: Environment :: Console
Classifier: Operating System :: OS Independent
Classifier: Intended Audience :: Developers
Classifier: Programming Language :: Python :: 3
Classifier: Programming Language :: Python :: 3.6
Classifier: Programming Language :: Python :: 3.7
Classifier: Programming Language :: Python :: 3.8
Requires-Python: >=3.6
